Pytanggalmerah-3.1.1.data/scripts/harilibur
pytanggalmerah/TanggalMerah.py
pytanggalmerah/__init__.py
pytanggalmerah/myrequests.py
Pytanggalmerah-3.1.1.dist-info/LICENSE.txt
Pytanggalmerah-3.1.1.dist-info/METADATA
Pytanggalmerah-3.1.1.dist-info/WHEEL
Pytanggalmerah-3.1.1.dist-info/top_level.txt
Pytanggalmerah-3.1.1.dist-info/RECORD
