Metadata-Version: 2.1
Name: Pytanggalmerah
Version: 3.1.1
Summary: python module to check indonesia holiday calendar (include sunday)
Home-page: https://github.com/guangrei/pytanggalmerah
Author: guangrei
Author-email: myawn@pm.me
License: MIT
Keywords: holiday indonesia calendar sunday
License-File: LICENSE.txt
Requires-Dist: requests
Requires-Dist: pytz
Requires-Dist: zcache
